[
  {
    "id": "sapporo_shusei",
    "name": "札幌酒精工業",
    "company": "札幌酒精工業株式会社",
    "brand": "喜多里",
    "type": "本格焼酎（麦・昆布・芋など）",
    "founded": "1933",
    "founded_era": "昭和8年",
    "address": "北海道札幌市西区発寒10条1丁目1番1号",
    "tel": "",
    "url": "https://www.sapporo-shusei.jp/",
    "area": "札幌市",
    "desc": "昭和8年創業の焼酎甲類メーカー。北海道南部・厚沢部町の自社工場にて原料の加工から一貫して本格焼酎「喜多里」を製造。甲類「サッポロソフト」も広く親しまれている。",
    "visit": "",
    "spirit_type": "honkaku",
    "koji_type": "",
    "main_ingredient": "麦",
    "brands": ["喜多里", "喜多里 昆布焼酎", "サッポロソフト"],
    "features": ["北海道産原料使用", "厚沢部工場で一貫生産"],
    "nearest_station": "",
    "source": "https://www.sapporo-shusei.jp/company/",
    "name_en": "Sapporo Shusei Kogyo"
  },
  {
    "id": "godo_shusei_asahikawa",
    "name": "合同酒精 旭川工場",
    "company": "合同酒精株式会社",
    "brand": "鍛高譚",
    "type": "しそ焼酎・甲類焼酎",
    "founded": "1900",
    "founded_era": "明治33年",
    "address": "北海道旭川市南6条通19丁目2182-103",
    "tel": "",
    "url": "https://www.oenon.jp/product/sake/sake-brewery/godo.html",
    "area": "旭川市",
    "desc": "初代神谷傳兵衛により1900年に開設。民間初のアルコール製造を開始して以来、蒸留技術の向上に取り組む。しそ焼酎「鍛高譚」は北海道白糠町産の赤シソを使用した人気銘柄。オエノングループ。",
    "visit": "",
    "spirit_type": "mixed",
    "koji_type": "",
    "main_ingredient": "しそ",
    "brands": ["鍛高譚", "大雪乃蔵"],
    "features": ["北海道白糠町産赤シソ使用", "オエノングループ"],
    "nearest_station": "",
    "source": "https://www.oenon.jp/product/sake/sake-brewery/godo.html",
    "name_en": "Godo Shusei Asahikawa Factory"
  }
]
